LICENSE
MANIFEST.in
README.md
VERSION
requirements.txt
setup.py
sqoopy/__init__.py
sqoopy.egg-info/PKG-INFO
sqoopy.egg-info/SOURCES.txt
sqoopy.egg-info/dependency_links.txt
sqoopy.egg-info/entry_points.txt
sqoopy.egg-info/not-zip-safe
sqoopy.egg-info/requires.txt
sqoopy.egg-info/top_level.txt