Metadata-Version: 1.1
Name: sqoopy
Version: 0.0.8.8
Summary: UNKNOWN
Home-page: http://github.com/voxmedia/sqoopy
Author: Brian Abelson
Author-email: brian.abelson@voxmedia.com
License: MIT
Keywords: sqoop,mysql,import,hadoop
Platform: UNKNOWN
Classifier: Development Status :: 3 - Alpha
Classifier: Intended Audience :: Developers
Classifier: License :: OSI Approved :: MIT License
Classifier: Operating System :: OS Independent
Classifier: Programming Language :: Python
